voltarium/__init__.py
voltarium/client.py
voltarium/exceptions.py
voltarium/factories/__init__.py
voltarium/factories/contracts.py
voltarium/factories/measurements.py
voltarium/factories/migration.py
voltarium/factories/token.py
voltarium/models/__init__.py
voltarium/models/constants.py
voltarium/models/contracts.py
voltarium/models/measurements.py
voltarium/models/migration.py
voltarium/models/requests.py
voltarium/models/token.py
voltarium/sandbox/__init__.py
voltarium/sandbox/models.py
voltarium/sandbox/retailers.py
voltarium/sandbox/utilities.py
voltarium-0.4.1.dist-info/WHEEL
voltarium-0.4.1.dist-info/METADATA
voltarium-0.4.1.dist-info/RECORD
