Metadata-Version: 2.3
Name: voltarium
Version: 0.4.1
Summary: Asynchronous Python client for CCEE (Brazilian Electric Energy Commercialization Chamber) API
Keywords: ccee,energy,brazil,api,async
Author: joaodaher
Author-email: joaodaher <joao@daher.dev>
License: 
Classifier: Development Status :: 3 - Alpha
Classifier: Intended Audience :: Developers
Classifier: License :: OSI Approved :: Apache Software License
Classifier: Operating System :: OS Independent
Classifier: Programming Language :: Python :: 3
Classifier: Programming Language :: Python :: 3.13
Classifier: Programming Language :: Python :: 3.14
Classifier: Topic :: Software Development :: Libraries :: Python Modules
Classifier: Topic :: Internet :: WWW/HTTP :: Dynamic Content
Requires-Dist: httpx>=0.28.1
Requires-Dist: pydantic>=2.11.7
Requires-Dist: tenacity>=9.1.2
Requires-Python: >=3.13
Project-URL: Bug Tracker, https://github.com/joaodaher/voltarium-python/issues
Project-URL: Documentation, https://github.com/joaodaher/voltarium-python
Project-URL: Homepage, https://github.com/joaodaher/voltarium-python
Project-URL: Repository, https://github.com/joaodaher/voltarium-python
